Workbook

Sheet SETTINGS
A1: DIVINE GRACE COOPERATIVE MULTIPURPOSE SOCIETY LIMITED
A2: ADMIN SETTINGS — Control Panel | REG NO: LSCS 18377 | TEL: 08038593189
A3: ⚙ All system-wide rates and rules are configured here. Only ADMIN can edit this sheet.
A4: Setting Key | B4: Description | C4: Value | D4: Unit
A5: WEEKLY_CONTRIBUTION | B5: Default weekly contribution per member | C5: 2000 | D5: ₦
A6: SAVINGS_PRORATION_PCT | B6: % of weekly contribution going to Savings (on loan) | C6: 60 | D6: %
A7: LOAN_REPAY_PRORATE_PCT | B7: % of weekly contribution going to Loan Repayment | C7: 40 | D7: %
A8: ALLOW_MEMBER_OVERRIDE | B8: Can member redirect 100% to loan repayment? | C8: YES | D8: YES/NO
A9: LOAN_INTEREST_RATE | B9: Annual loan interest rate | C9: 5 | D9: %
A10: MAX_LOAN_MULTIPLIER | B10: Maximum loan = X times member's total savings | C10: 2 | D10: ×
A11: MIN_MEMBERSHIP_MONTHS | B11: Minimum months of membership before loan | C11: 6 | D11: months
A12: MAX_GUARANTEES_PER_MBR | B12: Max number of loans a member can guarantee at once | C12: 2 | D12: loans
A13: SESSION_TIMEOUT_MINS | B13: Auto-logout after X minutes of inactivity | C13: 30 | D13: minutes
A14: ORG_NAME | B14: Organisation name | C14: Divine Grace Cooperative Multipurpose Society Limited
A15: ORG_REG | B15: Registration number | C15: LSCS 18377
A16: ORG_PHONE | B16: Organisation phone | C16: 08038593189

Sheet BRANCHES
A1: DIVINE GRACE COOPERATIVE MULTIPURPOSE SOCIETY LIMITED
A2: BRANCH REGISTRY | REG NO: LSCS 18377 | TEL: 08038593189
A3: BranchID | B3: Branch Name | C3: Address | D3: Phone | E3: Date Created | F3: Status
A4: BR001 | B4: Head Office | C4: 12 Cooperative Road, Surulere, Lagos | D4: 08038593189 | E4: 2020-01-01 | F4: Active
A5: BR002 | B5: Abuja Branch | C5: 45 Unity Avenue, Wuse II, Abuja | D5: 08012345678 | E5: 2021-03-15 | F5: Active
A6: BR003 | B6: Port Harcourt | C6: 7 Rumuola Road, Port Harcourt | D6: 08087654321 | E6: 2022-06-01 | F6: Active

Sheet MEMBERS
A1: DIVINE GRACE COOPERATIVE MULTIPURPOSE SOCIETY LIMITED
A2: MEMBER REGISTRY & ONBOARDING | REG NO: LSCS 18377 | TEL: 08038593189
A3: 🔵 Columns A–J = Core Info | K–R = Onboarding KYC | S–T = Eligibility (auto-calculated)
A4: MEM001 | B4: 0001 | C4: Grace | D4: Odunuga | E4: 08038593189 | F4: grace@email.com | G4: BR001 | H4: 2020-01-10 | I4: Active | J4: Founding member | K4: 1985-05-20 | L4: F | M4: 12 Coop Road, Lagos | N4: Teacher | O4: James Odunuga | P4: 08011112222 | Q4: Husband | R4: NIN | S4: 12345678901 | T4: =DATEDIF(H4,TODAY(),"M") -> 76 | U4: =H4+180 -> 44020 | V4: =SUMPRODUCT((TRANSACTIONS!C$5:C$500="MEM001")*(TRANSACTIONS!E$5:E$500="Savings")*(TRANSACTIONS!F$5:F$500="CR")*TRANSACTIONS!G$5:G$500)-SUMPRODUCT((TRANSACTIONS!C$5:C$500="MEM001")*(TRANSACTIONS!E$5:E$500="Savings")*(TRANSACTIONS!F$5:F$500="DR")*TRANSACTIONS!G$5:G$500) -> 1200 | W4: =V4*SETTINGS!$C$6 -> 72000 | Z4: Active | AA4: admin | AB4: 2020-01-08
A5: MEM002 | B5: 0002 | C5: Emeka | D5: Adebayo | E5: 08055551234 | F5: emeka@email.com | G5: BR001 | H5: 2020-02-01 | I5: Active | K5: 1990-08-15 | L5: M | M5: 45 Allen Ave, Lagos | N5: Engineer | O5: Mrs Adebayo | P5: 08033334444 | Q5: Mother | R5: BVN | S5: 22345678901 | T5: =DATEDIF(H5,TODAY(),"M") -> 76 | U5: =H5+180 -> 44042 | V5: =SUMPRODUCT((TRANSACTIONS!C$5:C$500="MEM002")*(TRANSACTIONS!E$5:E$500="Savings")*(TRANSACTIONS!F$5:F$500="CR")*TRANSACTIONS!G$5:G$500)-SUMPRODUCT((TRANSACTIONS!C$5:C$500="MEM002")*(TRANSACTIONS!E$5:E$500="Savings")*(TRANSACTIONS!F$5:F$500="DR")*TRANSACTIONS!G$5:G$500) -> 2000 | W5: =V5*SETTINGS!$C$6 -> 120000 | Z5: Active | AA5: admin | AB5: 2020-01-30

Sheet USERS
A1: DIVINE GRACE COOPERATIVE MULTIPURPOSE SOCIETY LIMITED
A2: USERS & ROLE-BASED ACCESS CONTROL | REG NO: LSCS 18377 | TEL: 08038593189
A3: 🔒 Passwords stored as SHA-256+Salt hash. Plain text NEVER stored. Roles: Admin=all | BranchManager=own branch | Member=own data only
A4: UserID | B4: MemberID | C4: Username | D4: Password (SHA-256+Salt) | E4: Role | F4: BranchID | G4: Last Login | H4: Status
A5: USR001 | B5: — | C5: admin | D5: [hashed_on_setup] | E5: Admin | F5: ALL | H5: Active
A6: USR002 | B6: MEM001 | C6: grace.odunuga | D6: [hashed] | E6: Member | F6: BR001 | H6: Active
A7: USR003 | B7: MEM002 | C7: emeka.adebayo | D7: [hashed] | E7: Member | F7: BR001 | H7: Active
A8: USR004 | B8: — | C8: mgr.abuja | D8: [hashed] | E8: BranchManager | F8: BR002 | H8: Active

Sheet TRANSACTIONS
A1: DIVINE GRACE COOPERATIVE MULTIPURPOSE SOCIETY LIMITED
A2: TRANSACTIONS — CR/DR LEDGER | REG NO: LSCS 18377 | TEL: 08038593189
A3: 💰 PRORATION: When member has active loan, contribution is split per SETTINGS rates. SplitType: Full=no loan | Savings=proration savings portion | LoanRepay=proration loan portion | Override=100% to loan
A4: TxnID | B4: Date | C4: MemberID | D4: BranchID | E4: Category | F4: Type | G4: Amount (₦) | H4: Running Balance (₦) | I4: Proration Applied | J4: Split Type | K4: Split Ref (TxnID) | L4: Remark | M4: Posted By
A5: TXN001 | B5: 2024-01-10 | C5: MEM001 | D5: BR001 | E5: Shares | F5: CR | G5: 244 | H5: 244 | I5: No | J5: Full | K5: — | L5: Opening shares | M5: admin
A6: TXN002 | B6: 2024-01-10 | C6: MEM001 | D6: BR001 | E6: Savings | F6: CR | G6: 1200 | H6: 1200 | I6: Yes | J6: Savings | K6: TXN003 | L6: Proration: 60% of ₦2000 | M6: admin
A7: TXN003 | B7: 2024-01-10 | C7: MEM001 | D7: BR001 | E7: Loan | F7: DR | G7: 800 | H7: 800 | I7: Yes | J7: LoanRepay | K7: TXN002 | L7: Proration: 40% of ₦2000 | M7: admin
A8: TXN004 | B8: 2024-02-10 | C8: MEM002 | D8: BR001 | E8: Savings | F8: CR | G8: 2000 | H8: 3200 | I8: No | J8: Full | K8: — | L8: Full contribution, no loan | M8: admin

Sheet LOANS
A1: DIVINE GRACE COOPERATIVE MULTIPURPOSE SOCIETY LIMITED
A2: LOAN APPLICATIONS & LIFECYCLE | REG NO: LSCS 18377 | TEL: 08038593189
A3: 📋 LIFECYCLE: Pending → Approved/Rejected → Active (disbursed) → Closed (fully repaid) | ONE LOAN PER MEMBER at a time | Max = 2× Savings | Min 6 months membership
A4: LoanID | B4: MemberID | C4: BranchID | D4: Principal (₦) | E4: Interest Rate (%) | F4: Interest Amt (₦) | G4: Total Due (₦) | H4: Total Repaid (₦) | I4: Outstanding (₦) | J4: Purpose | K4: Duration (Months) | L4: Application Date | M4: Status | N4: Approved By | O4: Approval Date | P4: Disbursement Date | Q4: Remarks
A5: LN001 | B5: MEM001 | C5: BR001 | D5: 50000 | E5: =SETTINGS!C5 -> 2000 | F5: =D5*E5/100 -> 1000000 | G5: =D5+F5 -> 1050000 | H5: =SUMPRODUCT((LOAN_REPAYMENTS!B$5:B$400="LN001")*LOAN_REPAYMENTS!F$5:F$400) -> 30000 | I5: =G5-H5 -> 1020000 | J5: Business capital | K5: 6 | L5: 2024-03-01 | M5: Active | N5: admin | O5: 2024-03-05 | P5: 2024-03-07 | Q5: Approved after verification
A6: LN002 | B6: MEM002 | C6: BR001 | D6: 100000 | E6: =SETTINGS!C5 -> 2000 | F6: =D6*E6/100 -> 2000000 | G6: =D6+F6 -> 2100000 | H6: =SUMPRODUCT((LOAN_REPAYMENTS!B$5:B$400="LN002")*LOAN_REPAYMENTS!F$5:F$400) -> 0 | I6: =G6-H6 -> 2100000 | J6: School fees | K6: 12 | L6: 2024-04-01 | M6: Pending | Q6: Awaiting guarantor verification

Sheet LOAN_REPAYMENTS
A1: DIVINE GRACE COOPERATIVE MULTIPURPOSE SOCIETY LIMITED
A2: LOAN REPAYMENT TRACKER | REG NO: LSCS 18377 | TEL: 08038593189
A3: 💳 Each repayment reduces the Outstanding Balance in LOANS sheet automatically via formula.
A4: RepaymentID | B4: LoanID | C4: MemberID | D4: BranchID | E4: Date | F4: Amount Paid (₦) | G4: Outstanding After (₦) | H4: Remark | I4: Posted By
A5: REP001 | B5: LN001 | C5: MEM001 | D5: BR001 | E5: 2024-04-07 | F5: 10000 | G5: 40000 | H5: Monthly repayment 1 | I5: admin
A6: REP002 | B6: LN001 | C6: MEM001 | D6: BR001 | E6: 2024-05-07 | F6: 10000 | G6: 30000 | H6: Monthly repayment 2 | I6: admin
A7: REP003 | B7: LN001 | C7: MEM001 | D7: BR001 | E7: 2024-06-07 | F7: 10000 | G7: 20000 | H7: Monthly repayment 3 | I7: admin

Sheet GUARANTORS
A1: DIVINE GRACE COOPERATIVE MULTIPURPOSE SOCIETY LIMITED
A2: LOAN GUARANTORS REGISTRY | REG NO: LSCS 18377 | TEL: 08038593189
A3: 🤝 Each loan requires 2 guarantors. Guarantors must be: Active members | No outstanding loan | Not the applicant | Not already guaranteeing max loans
A4: GuarantorID | B4: LoanID | C4: Applicant MemberID | D4: Guarantor MemberID | E4: Guarantor CoopNo | F4: Guarantor Name | G4: Guarantor Phone | H4: Consent Given | I4: Verification Status | J4: Date Provided
A5: GUA001 | B5: LN001 | C5: MEM001 | D5: MEM002 | E5: 0002 | F5: Emeka Adebayo | G5: 08055551234 | H5: YES | I5: Verified | J5: 2024-03-01
A6: GUA002 | B6: LN001 | C6: MEM001 | D6: MEM003 | E6: 0003 | F6: Fatima Musa | G6: 08077778888 | H6: YES | I6: Verified | J6: 2024-03-01
A7: GUA003 | B7: LN002 | C7: MEM002 | D7: MEM001 | E7: 0001 | F7: Grace Odunuga | G7: 08038593189 | H7: YES | I7: Pending | J7: 2024-04-01
A8: GUA004 | B8: LN002 | C8: MEM002 | D8: MEM004 | E8: 0004 | F8: Chidi Okonkwo | G8: 08099990000 | H8: NO | I8: Pending | J8: 2024-04-01

Sheet COMMODITIES
A1: DIVINE GRACE COOPERATIVE MULTIPURPOSE SOCIETY LIMITED
A2: COMMODITIES — GOODS ISSUED TO MEMBERS | REG NO: LSCS 18377 | TEL: 08038593189
A3: CommodityID | B3: MemberID | C3: BranchID | D3: Item Description | E3: Quantity | F3: Unit Price (₦) | G3: Total Value (₦) | H3: Date Issued | I3: Payment Status | J3: Amount Paid (₦) | K3: Balance Due (₦)
A4: COM001 | B4: MEM001 | C4: BR001 | D4: Rice (50kg bag) | E4: 2 | F4: 35000 | G4: =F4*E4 -> 70000 | H4: 2024-02-01 | I4: Partial | J4: 30000 | K4: =G4-J4 -> 40000
A5: COM002 | B5: MEM002 | C5: BR001 | D5: Fertilizer (25kg) | E5: 5 | F5: 12000 | G5: =F5*E5 -> 60000 | H5: 2024-03-15 | I5: Paid | J5: =G5 -> 60000 | K5: =G5-J5 -> 0
A6: COM003 | B6: MEM003 | C6: BR002 | D6: Palm oil (25L kegs) | E6: 3 | F6: 18000 | G6: =F6*E6 -> 54000 | H6: 2024-04-01 | I6: Unpaid | J6: 0 | K6: =G6-J6 -> 54000

Sheet SUMMARY
A1: DIVINE GRACE COOPERATIVE MULTIPURPOSE SOCIETY LIMITED
A2: SUMMARY DASHBOARD — AUTO-CALCULATED | REG NO: LSCS 18377 | TEL: 08038593189
A3: ⚠ READ ONLY — Auto-populated by Apps Script. Do NOT edit manually. Reflects real-time balances per member across all categories.
A4: MemberID | B4: Full Name | C4: Branch | D4: Shares Bal (₦) | E4: Savings Bal (₦) | F4: Loan Outstanding (₦) | G4: Deposit Bal (₦) | H4: Commodity Due (₦) | I4: Loan Status | J4: Last Updated

Sheet README
A1: DIVINE GRACE COOPERATIVE MULTIPURPOSE SOCIETY LIMITED
A2: SYSTEM GUIDE & BUSINESS RULES | REG NO: LSCS 18377 | TEL: 08038593189
A3: SHEET GUIDE
A4: Sheet | Purpose | Who Edits | Key Link
A5: SETTINGS | Admin rates & rules | Admin only | Source of all rates
A6: BRANCHES | Branch registry | Admin only | BranchID links everywhere
A7: MEMBERS | Member profiles + onboarding + eligibility formulas | Admin | MemberID is master key
A8: USERS | Login + roles (Admin/BranchManager/Member) | Admin only | Password hashed SHA-256+Salt
A9: TRANSACTIONS | Every CR/DR entry with proration support | Admin/Manager | Links MEMBERS+BRANCHES
A10: LOANS | Full loan lifecycle Pending→Active→Closed | Admin | Links MEMBERS+GUARANTORS+REPAYMENTS
A11: LOAN_REPAYMENTS | Each repayment posted here | Admin | LoanID links to LOANS
A12: GUARANTORS | 2 guarantors per loan, verified here | Admin | Links LOANS+MEMBERS
... A32: 🔒 Google AES-256 encryption at rest | HTTPS/TLS in transit
